examples/__init__.py
examples/arabic/__init__.py
examples/arabic/quran/__init__.py
examples/arabic/quran/assembler.py
examples/arabic/quran/evaluate_permutations.py
examples/arabic/quran/quran_question_answering.py
examples/arabic/quran/quranqa22_eval.py
examples/arabic/quran/quranqa22_submission_checker.py
examples/arabic/quran/transfer_learning_model_generation.py
examples/arabic/quran/data/__init__.py
examples/arabic/quran/data/preprocess/__init__.py
examples/arabic/quran/data/preprocess/read_write_qrcd.py
questionanswering/__init__.py
questionanswering/transformers/__init__.py
questionanswering/transformers/question_answering_model.py
questionanswering/transformers/question_answering_utils.py
questionanswering/transformers/config/__init__.py
questionanswering/transformers/config/global_args.py
questionanswering/transformers/config/model_args.py
questionanswering/transformers/config/utils.py
questionanswering/transformers/custom_models/__init__.py
questionanswering/transformers/custom_models/models.py
questionanswering/transformers/qa_dataset_loading_script/__init__.py
questionanswering/transformers/qa_dataset_loading_script/qa_dataset_loading_script.py
quesans-0.0.1.dist-info/LICENSE
quesans-0.0.1.dist-info/METADATA
quesans-0.0.1.dist-info/WHEEL
quesans-0.0.1.dist-info/top_level.txt
quesans-0.0.1.dist-info/RECORD
