Metadata-Version: 2.1
Name: quesans
Version: 0.0.1
Summary: Deep Learning based Questions Answering package
Home-page: https://github.com/DamithDR/QuestionAnswering
Author: Damith Premasiri
Author-email: damithpremasiri@gmail.com
License: UNKNOWN
Platform: UNKNOWN
Classifier: Intended Audience :: Science/Research
Classifier: License :: OSI Approved :: Apache Software License
Classifier: Programming Language :: Python :: 3
Classifier: Topic :: Scientific/Engineering :: Artificial Intelligence
Requires-Python: >=3.6
License-File: LICENSE
Requires-Dist: transformers (==4.16.2)
Requires-Dist: tensorboard
Requires-Dist: datasets (==1.18.3)
Requires-Dist: numpy (==1.22.2)
Requires-Dist: pandas (==1.4.0)
Requires-Dist: tqdm (==4.62.3)
Requires-Dist: farasapy
Requires-Dist: PyArabic (~=0.6.14)
